rasterfoundry/__init__.py
rasterfoundry/api.py
rasterfoundry/exceptions.py
rasterfoundry/spec.yml
rasterfoundry/models/__init__.py
rasterfoundry/models/project.py
rasterfoundry-0.1.0.dist-info/DESCRIPTION.rst
rasterfoundry-0.1.0.dist-info/METADATA
rasterfoundry-0.1.0.dist-info/RECORD
rasterfoundry-0.1.0.dist-info/WHEEL
rasterfoundry-0.1.0.dist-info/metadata.json
rasterfoundry-0.1.0.dist-info/top_level.txt
