Metadata-Version: 2.0
Name: rasterfoundry
Version: 0.1.0
Summary: A Python client for Raster Foundry, a web platform for combining, analyzing, and publishing raster data.
Home-page: https://github.com/azavea/raster-foundry-python-client
Author: Raster Foundry
Author-email: info@rasterfoundry.com
License: Apache License 2.0
Keywords: raster earth-observation geospatial geospatial-processing
Platform: UNKNOWN
Classifier: Intended Audience :: Developers
Classifier: License :: OSI Approved :: Apache Software License
Classifier: Programming Language :: Python
Classifier: Programming Language :: Python :: 2
Classifier: Programming Language :: Python :: 3
Requires-Dist: bravado (>=8.4.0)
Requires-Dist: cryptography (>=1.3.2)
Requires-Dist: pyasn1 (>=0.2.3)
Requires-Dist: requests (>=2.9.1)
Provides-Extra: dev
Provides-Extra: test
